installer.py
node_installer-0.1.0.dist-info/License.txt
node_installer-0.1.0.dist-info/METADATA
node_installer-0.1.0.dist-info/WHEEL
node_installer-0.1.0.dist-info/entry_points.txt
node_installer-0.1.0.dist-info/top_level.txt
node_installer-0.1.0.dist-info/RECORD
