Metadata-Version: 2.2
Name: node-installer
Version: 0.1.0
Summary: Install Node.js silently via CMD on Windows
Author: Antony
Classifier: Programming Language :: Python :: 3
Classifier: Operating System :: Microsoft :: Windows
Classifier: License :: OSI Approved :: MIT License
Requires-Python: >=3.6
License-File: License.txt
Dynamic: author
Dynamic: classifier
Dynamic: requires-python
Dynamic: summary
